approck_aiogram_utils/__init__.py
approck_aiogram_utils/callback.py
approck_aiogram_utils/integration/__init__.py
approck_aiogram_utils/integration/uprock/__init__.py
approck_aiogram_utils/integration/uprock/app.py
approck_aiogram_utils/integration/uprock/events.py
approck_aiogram_utils/integration/uprock/handlers.py
approck_aiogram_utils/integration/uprock/sentry.py
approck_aiogram_utils/message.py
approck_aiogram_utils-0.2.23.dist-info/METADATA
approck_aiogram_utils-0.2.23.dist-info/WHEEL
approck_aiogram_utils-0.2.23.dist-info/RECORD
