Metadata-Version: 2.3
Name: approck-aiogram-utils
Version: 0.2.23
Summary: 
Author: Aleksey Dalekin
Author-email: ald@approck.pro
Requires-Python: >=3.10,<4.0
Classifier: Programming Language :: Python :: 3
Classifier: Programming Language :: Python :: 3.10
Classifier: Programming Language :: Python :: 3.11
Classifier: Programming Language :: Python :: 3.12
Classifier: Programming Language :: Python :: 3.13
Provides-Extra: events
Provides-Extra: sentry
Provides-Extra: transport
Provides-Extra: uprock
Requires-Dist: aiogram (>=3.7.0,<4.0.0)
Requires-Dist: approck-events-sdk (>=0.1.6) ; extra == "events"
Requires-Dist: approck-messaging (>=0.1.9) ; extra == "transport"
Requires-Dist: approck-messaging[transport] (>=0.1.9) ; extra == "transport"
Requires-Dist: loguru (>=0.7.2,<0.8.0)
Requires-Dist: pydantic-settings (>=2.1.0,<3.0.0)
Requires-Dist: pydantic[dotenv,email] (>=2.4.1)
Requires-Dist: sentry-sdk (>=2.5.1,<3.0.0) ; extra == "sentry"
Requires-Dist: uprock-sdk (>=0.1.43,<0.2.0) ; extra == "uprock"
